braintree/__init__.py
braintree/account_updater_daily_report.py
braintree/add_on.py
braintree/add_on_gateway.py
braintree/address.py
braintree/address_gateway.py
braintree/amex_express_checkout_card.py
braintree/android_pay_card.py
braintree/apple_pay_card.py
braintree/attribute_getter.py
braintree/braintree_gateway.py
braintree/client_token.py
braintree/client_token_gateway.py
braintree/coinbase_account.py
braintree/configuration.py
braintree/credentials_parser.py
braintree/credit_card.py
braintree/credit_card_gateway.py
braintree/credit_card_verification.py
braintree/credit_card_verification_gateway.py
braintree/credit_card_verification_search.py
braintree/customer.py
braintree/customer_gateway.py
braintree/customer_search.py
braintree/descriptor.py
braintree/disbursement.py
braintree/disbursement_detail.py
braintree/discount.py
braintree/discount_gateway.py
braintree/dispute.py
braintree/environment.py
braintree/error_codes.py
braintree/error_result.py
braintree/errors.py
braintree/europe_bank_account.py
braintree/facilitator_details.py
braintree/ids_search.py
braintree/merchant.py
braintree/merchant_account_gateway.py
braintree/merchant_gateway.py
braintree/modification.py
braintree/oauth_credentials.py
braintree/oauth_gateway.py
braintree/partner_merchant.py
braintree/payment_instrument_type.py
braintree/payment_method.py
braintree/payment_method_gateway.py
braintree/payment_method_nonce.py
braintree/payment_method_nonce_gateway.py
braintree/paypal_account.py
braintree/paypal_account_gateway.py
braintree/plan.py
braintree/plan_gateway.py
braintree/resource.py
braintree/resource_collection.py
braintree/risk_data.py
braintree/search.py
braintree/settlement_batch_summary.py
braintree/settlement_batch_summary_gateway.py
braintree/signature_service.py
braintree/status_event.py
braintree/subscription.py
braintree/subscription_details.py
braintree/subscription_gateway.py
braintree/subscription_search.py
briantree-3.30.0.dist-info/DESCRIPTION.rst
briantree-3.30.0.dist-info/METADATA
briantree-3.30.0.dist-info/RECORD
briantree-3.30.0.dist-info/WHEEL
briantree-3.30.0.dist-info/metadata.json
briantree-3.30.0.dist-info/top_level.txt
