Metadata-Version: 2.0
Name: briantree
Version: 3.30.0
Summary: Braintree Python Library
Home-page: https://developers.braintreepayments.com/python/sdk/server/overview
Author: Braintree
Author-email: support@braintreepayments.com
License: UNKNOWN
Platform: UNKNOWN
Classifier: Programming Language :: Python :: 2.6
Classifier: Programming Language :: Python :: 2.7
Classifier: Programming Language :: Python :: 3.3
Classifier: Programming Language :: Python :: 3.4
Classifier: Programming Language :: Python :: 3.5
Requires-Dist: requests (<3.0,>=0.11.1)
